trovesuite/__init__.py
trovesuite/auth/__init__.py
trovesuite/auth/auth_base.py
trovesuite/auth/auth_controller.py
trovesuite/auth/auth_read_dto.py
trovesuite/auth/auth_service.py
trovesuite/auth/auth_write_dto.py
trovesuite/configs/__init__.py
trovesuite/configs/database.py
trovesuite/configs/logging.py
trovesuite/configs/settings.py
trovesuite/entities/__init__.py
trovesuite/entities/health.py
trovesuite/entities/sh_response.py
trovesuite/notification/__init__.py
trovesuite/notification/notification_base.py
trovesuite/notification/notification_controller.py
trovesuite/notification/notification_read_dto.py
trovesuite/notification/notification_service.py
trovesuite/notification/notification_write_dto.py
trovesuite/storage/__init__.py
trovesuite/storage/storage_base.py
trovesuite/storage/storage_controller.py
trovesuite/storage/storage_read_dto.py
trovesuite/storage/storage_service.py
trovesuite/storage/storage_write_dto.py
trovesuite/utils/__init__.py
trovesuite/utils/helper.py
trovesuite/utils/templates.py
trovesuite-1.0.33.dist-info/licenses/LICENSE
trovesuite-1.0.33.dist-info/METADATA
trovesuite-1.0.33.dist-info/WHEEL
trovesuite-1.0.33.dist-info/top_level.txt
trovesuite-1.0.33.dist-info/RECORD
