Metadata-Version: 2.4
Name: trovesuite
Version: 1.0.33
Summary: TroveSuite services package providing authentication, authorization, notifications, Azure Storage, and other enterprise services for TroveSuite applications
Home-page: https://dev.azure.com/brightgclt/trovesuite/_git/packages
Author: Bright Debrah Owusu
Author-email: Bright Debrah Owusu <owusu.debrah@deladetech.com>
Maintainer-email: Bright Debrah Owusu <owusu.debrah@deladetech.com>
License: MIT
Project-URL: Homepage, https://dev.azure.com/brightgclt/trovesuite/_git/packages
Project-URL: Repository, https://dev.azure.com/brightgclt/trovesuite/_git/packages
Project-URL: Documentation, https://dev.azure.com/brightgclt/trovesuite/_git/packages
Project-URL: Bug Tracker, https://dev.azure.com/brightgclt/trovesuite/_workitems/create
Keywords: authentication,authorization,notifications,jwt,trovesuite,fastapi,security,tenant,permissions,enterprise,services,azure,storage,blob,cloud-storage
Classifier: Development Status :: 5 - Production/Stable
Classifier: Intended Audience :: Developers
Classifier: License :: OSI Approved :: MIT License
Classifier: Operating System :: OS Independent
Classifier: Programming Language :: Python :: 3
Classifier: Programming Language :: Python :: 3.11
Classifier: Programming Language :: Python :: 3.12
Classifier: Programming Language :: Python :: 3.13
Classifier: Topic :: Software Development :: Libraries :: Python Modules
Classifier: Topic :: Internet :: WWW/HTTP :: Dynamic Content
Classifier: Topic :: Security
Requires-Python: >=3.12
License-File: LICENSE
Requires-Dist: fastapi>=0.116.1
Requires-Dist: pydantic>=2.11.9
Requires-Dist: psycopg2-binary>=2.9.9
Requires-Dist: python-dotenv>=1.0.0
Requires-Dist: python-multipart>=0.0.6
Requires-Dist: python-jose[cryptography]>=3.3.0
Requires-Dist: passlib[bcrypt]>=1.7.4
Requires-Dist: passlib[argon2]<2.0.0,>=1.7.4
Requires-Dist: uvicorn<0.39.0,>=0.38.0
Requires-Dist: pyjwt<3.0.0,>=2.10.1
Requires-Dist: azure-storage-blob>=12.19.0
Requires-Dist: azure-identity>=1.15.0
Provides-Extra: dev
Requires-Dist: pytest>=8.4.2; extra == "dev"
Requires-Dist: pytest-asyncio>=0.21.1; extra == "dev"
Requires-Dist: pytest-cov>=4.1.0; extra == "dev"
Requires-Dist: pytest-mock>=3.12.0; extra == "dev"
Requires-Dist: factory-boy>=3.3.0; extra == "dev"
Requires-Dist: faker>=20.1.0; extra == "dev"
Requires-Dist: black>=23.11.0; extra == "dev"
Requires-Dist: mypy>=1.0.0; extra == "dev"
Requires-Dist: flake8>=6.0.0; extra == "dev"
Dynamic: author
Dynamic: home-page
Dynamic: license-file
Dynamic: requires-python
